[
    {
        "label": "Overview",
        "rows": [
            [
                {
                    "name": "name"
                }
            ],
            [
                {
                    "name": "status"
                }
            ],
            [
                {
                    "name": "channelType"
                }
            ],
            [
                {
                    "name": "phoneNumber"
                }
            ],
            [
                {
                    "name": "whatsappName"
                }
            ],
            [
                {
                    "name": "chatwootAccount"
                }
            ],
            [
                {
                    "name": "oAuthAccount"
                }
            ],
            [
                {
                    "name": "businessAccountId"
                }
            ]
        ]
    }
]
