{
    "Settings": {
        "userInterface": {
            "module": "Global"
        }
    },
    "Preferences": {
        "detail": {
            "module": "Global"
        }
    },
    "Account": {
        "detail": {
            "module": "Global"
        },
        "bottomPanelsDetail": {
            "module": "Global"
        },
        "sidePanelsDetail": {
            "module": "Global"
        }
    },
    "Contact": {
        "detail": {
            "module": "Global"
        },
        "bottomPanelsDetail": {
            "module": "Global"
        },
        "sidePanelsDetail": {
            "module": "Global"
        }
    },
    "Opportunity": {
        "detail": {
            "module": "Global"
        },
        "filters": {
            "module": "Global"
        },
        "list": {
            "module": "Global"
        }
    }
}

